{
  "ideas": [
    {
      "id": "rec4TTVYYR1lc3",
      "cardId": "CARD001",
      "content": "今天看到一只可爱的猫咪",
      "author": "小猫咪爱好者",
      "submitter": "aki",
      "images": [],
      "createdAt": "2026-04-17T11:56:42.000Z",
      "tags": "灵感"
    },
    {
      "id": "recRptFTQFH1eN",
      "cardId": "CARD002",
      "content": "童年的回忆，那部老电影",
      "author": "电影迷小李",
      "submitter": "aki",
      "images": [],
      "createdAt": "2026-04-17T11:56:42.000Z",
      "tags": "故事"
    },
    {
      "id": "recKWe0r4iUH1d",
      "cardId": "CARD003",
      "content": "夕阳下的海边，金色的沙滩",
      "author": "摄影爱好者",
      "submitter": "aki",
      "images": [],
      "createdAt": "2026-04-17T11:56:42.000Z",
      "tags": "画面描述"
    },
    {
      "id": "recx4Yu6PCYZPD",
      "cardId": "CARD004",
      "content": "一张星空的照片，很美",
      "author": "天文爱好者",
      "submitter": "aki",
      "images": [],
      "createdAt": "2026-04-17T11:56:42.000Z",
      "tags": "参考图"
    },
    {
      "id": "rec06iAXPd14OQ",
      "cardId": "CARD005",
      "content": "关于未来科技的想法",
      "author": "科技畅想者",
      "submitter": "aki",
      "images": [],
      "createdAt": "2026-04-17T11:56:42.000Z",
      "tags": "其他"
    },
    {
      "id": "reccv9QsHTyHCC",
      "cardId": "CARD006",
      "content": "妈妈做的红烧肉，味道超赞",
      "author": "美食家小厨",
      "submitter": "aki",
      "images": [],
      "createdAt": "2026-04-17T11:56:42.000Z",
      "tags": "故事"
    },
    {
      "id": "recjYF03GxR9HB",
      "cardId": "CARD007",
      "content": "雨后的森林，清新的空气",
      "author": "自然探索者",
      "submitter": "aki",
      "images": [],
      "createdAt": "2026-04-17T11:56:42.000Z",
      "tags": "画面描述"
    },
    {
      "id": "rec4LpzS6Gl1yY",
      "cardId": "CARD008",
      "content": "一本经典的小说封面",
      "author": "文学爱好者",
      "submitter": "aki",
      "images": [],
      "createdAt": "2026-04-17T11:56:42.000Z",
      "tags": "参考图"
    },
    {
      "id": "recPfIAss4gttO",
      "cardId": "CARD009",
      "content": "旅行中遇到的有趣故事",
      "author": "背包客阿明",
      "submitter": "aki",
      "images": [],
      "createdAt": "2026-04-17T11:56:42.000Z",
      "tags": "故事"
    },
    {
      "id": "recCZvupGtZy0j",
      "cardId": "CARD010",
      "content": "新的一年，新的计划",
      "author": "规划达人",
      "submitter": "aki",
      "images": [],
      "createdAt": "2026-04-17T11:56:42.000Z",
      "tags": "其他"
    },
    {
      "id": "rec5YZrjDI3SD8",
      "cardId": "CARD001",
      "content": "今天突然有了一个关于宇宙探索的灵感",
      "author": "张三",
      "submitter": "aki",
      "images": [],
      "createdAt": "2026-04-17T11:46:34.000Z",
      "tags": "灵感"
    },
    {
      "id": "recIKkR1fxeC1L",
      "cardId": "CARD002",
      "content": "小时候和爷爷一起去海边的故事",
      "author": "李四",
      "submitter": "aki",
      "images": [],
      "createdAt": "2026-04-17T11:46:34.000Z",
      "tags": "故事"
    },
    {
      "id": "recJkei9PNqiw1",
      "cardId": "CARD003",
      "content": "夕阳下金色沙滩上的海鸥和海浪",
      "author": "王五",
      "submitter": "aki",
      "images": [],
      "createdAt": "2026-04-17T11:46:34.000Z",
      "tags": "画面描述"
    },
    {
      "id": "recbv0QjMdvMLU",
      "cardId": "CARD004",
      "content": "https://himematsu.oss-cn-guangzhou.aliyuncs.com/hnu-timeletter/eb0efc060991feb8f3cf4ffcd426b4c7.png",
      "author": "赵六",
      "submitter": "aki",
      "images": [
        "https://himematsu.oss-cn-guangzhou.aliyuncs.com/hnu-timeletter/eb0efc060991feb8f3cf4ffcd426b4c7.png"
      ],
      "createdAt": "2026-04-17T11:46:34.000Z",
      "tags": "参考图"
    },
    {
      "id": "recm1p8GugPnSj",
      "cardId": "CARD005",
      "content": "关于未来城市交通的一些想法",
      "author": "钱七",
      "submitter": "aki",
      "images": [],
      "createdAt": "2026-04-17T11:46:34.000Z",
      "tags": "其他"
    },
    {
      "id": "recv5MrP5JpmZH",
      "cardId": "CARD006",
      "content": "新的编程框架带来的技术灵感",
      "author": "孙八",
      "submitter": "aki",
      "images": [],
      "createdAt": "2026-04-17T11:46:34.000Z",
      "tags": "灵感"
    },
    {
      "id": "recxl15Kl7bMem",
      "cardId": "CARD007",
      "content": "童年时第一次养宠物的温馨故事",
      "author": "周九",
      "submitter": "aki",
      "images": [],
      "createdAt": "2026-04-17T11:46:34.000Z",
      "tags": "故事"
    },
    {
      "id": "recgRHbRej9R8I",
      "cardId": "CARD008",
      "content": "雨后森林中蘑菇和苔藓的特写",
      "author": "吴十",
      "submitter": "aki",
      "images": [],
      "createdAt": "2026-04-17T11:46:34.000Z",
      "tags": "画面描述"
    },
    {
      "id": "recnk4KKH9xufk",
      "cardId": "CARD009",
      "content": "https://himematsu.oss-cn-guangzhou.aliyuncs.com/hnu-timeletter/26bb2a29a597542a5dcb44b04d8b909d.jpg",
      "author": "郑十一",
      "submitter": "aki",
      "images": [
        "https://himematsu.oss-cn-guangzhou.aliyuncs.com/hnu-timeletter/26bb2a29a597542a5dcb44b04d8b909d.jpg"
      ],
      "createdAt": "2026-04-17T11:46:34.000Z",
      "tags": "参考图"
    },
    {
      "id": "recsysC3bhGa4G",
      "cardId": "CARD010",
      "content": "关于环保材料的创新设计",
      "author": "王十二",
      "submitter": "aki",
      "images": [],
      "createdAt": "2026-04-17T11:46:34.000Z",
      "tags": "其他"
    }
  ]
}